{
  "sucursales": [
    "Principal"
  ],
  "data": {
    "Principal": {
      "2026-05": {
        "p1_llave1": true,
        "p1_llave2": true,
        "p1_venta_rep": 79,
        "p1_paso_veh": 79.1,
        "p1_paso_veh_real": 153,
        "p1_campanas": 100,
        "p1_mpp": 0,
        "p2_cumpl": null,
        "p2_vor_cargo": 0,
        "p2_facturacion": null,
        "p3_poliza": null,
        "p3_dyp": null,
        "p3_fact_seguros": null,
        "p3_fact_dyp": null,
        "p4_nps": 85.9,
        "p4_tasa_resp": 47.9,
        "p4_facturacion": 0,
        "p4_n_resp": 78,
        "p4_n_total": null,
        "sc_pv": null,
        "sc_autos": 0,
        "sc_dias_adicional": 0,
        "sc_modelo": "",
        "cap_pres": null,
        "cap_pres_falt": 0,
        "cap_online": 100,
        "cap_online_falt": 0,
        "cap_id_viz": null,
        "cap_id_comp": null,
        "cap_cert1": null,
        "cap_cert2": null,
        "cap_uf": 38500,
        "cm_ot": 153,
        "cm_envios": 153,
        "cm_cotizacion": 90,
        "cm_aprobado": 50
      },
      "2025-06": {
        "p1_llave1": true,
        "p1_llave2": true,
        "p1_venta_rep": null,
        "p1_paso_veh": null,
        "p1_paso_veh_real": null,
        "p1_campanas": null,
        "p1_mpp": null,
        "p2_cumpl": null,
        "p2_vor_cargo": 0,
        "p2_facturacion": null,
        "p3_poliza": null,
        "p3_dyp": null,
        "p3_fact_seguros": null,
        "p3_fact_dyp": null,
        "p4_nps": null,
        "p4_tasa_resp": null,
        "p4_facturacion": null,
        "p4_n_resp": null,
        "p4_n_total": null,
        "sc_pv": null,
        "sc_autos": null,
        "sc_dias_adicional": 0,
        "sc_modelo": "",
        "cap_pres": null,
        "cap_pres_falt": 0,
        "cap_online": null,
        "cap_online_falt": 0,
        "cap_id_viz": null,
        "cap_id_comp": null,
        "cap_cert1": null,
        "cap_cert2": null,
        "cap_uf": 38500,
        "cm_ot": null,
        "cm_envios": null,
        "cm_cotizacion": null,
        "cm_aprobado": null
      },
      "2025-07": {
        "p1_llave1": true,
        "p1_llave2": true,
        "p1_venta_rep": null,
        "p1_paso_veh": null,
        "p1_paso_veh_real": null,
        "p1_campanas": null,
        "p1_mpp": null,
        "p2_cumpl": null,
        "p2_vor_cargo": 0,
        "p2_facturacion": null,
        "p3_poliza": null,
        "p3_dyp": null,
        "p3_fact_seguros": null,
        "p3_fact_dyp": null,
        "p4_nps": null,
        "p4_tasa_resp": null,
        "p4_facturacion": null,
        "p4_n_resp": null,
        "p4_n_total": null,
        "sc_pv": null,
        "sc_autos": null,
        "sc_dias_adicional": 0,
        "sc_modelo": "",
        "cap_pres": null,
        "cap_pres_falt": 0,
        "cap_online": null,
        "cap_online_falt": 0,
        "cap_id_viz": null,
        "cap_id_comp": null,
        "cap_cert1": null,
        "cap_cert2": null,
        "cap_uf": 38500,
        "cm_ot": null,
        "cm_envios": null,
        "cm_cotizacion": null,
        "cm_aprobado": null
      },
      "2025-08": {
        "p1_llave1": true,
        "p1_llave2": true,
        "p1_venta_rep": null,
        "p1_paso_veh": null,
        "p1_paso_veh_real": null,
        "p1_campanas": null,
        "p1_mpp": null,
        "p2_cumpl": null,
        "p2_vor_cargo": 0,
        "p2_facturacion": null,
        "p3_poliza": null,
        "p3_dyp": null,
        "p3_fact_seguros": null,
        "p3_fact_dyp": null,
        "p4_nps": null,
        "p4_tasa_resp": null,
        "p4_facturacion": null,
        "p4_n_resp": null,
        "p4_n_total": null,
        "sc_pv": null,
        "sc_autos": null,
        "sc_dias_adicional": 0,
        "sc_modelo": "",
        "cap_pres": null,
        "cap_pres_falt": 0,
        "cap_online": null,
        "cap_online_falt": 0,
        "cap_id_viz": null,
        "cap_id_comp": null,
        "cap_cert1": null,
        "cap_cert2": null,
        "cap_uf": 38500,
        "cm_ot": null,
        "cm_envios": null,
        "cm_cotizacion": null,
        "cm_aprobado": null
      },
      "2025-09": {
        "p1_llave1": true,
        "p1_llave2": true,
        "p1_venta_rep": null,
        "p1_paso_veh": null,
        "p1_paso_veh_real": null,
        "p1_campanas": null,
        "p1_mpp": null,
        "p2_cumpl": null,
        "p2_vor_cargo": 0,
        "p2_facturacion": null,
        "p3_poliza": null,
        "p3_dyp": null,
        "p3_fact_seguros": null,
        "p3_fact_dyp": null,
        "p4_nps": null,
        "p4_tasa_resp": null,
        "p4_facturacion": null,
        "p4_n_resp": null,
        "p4_n_total": null,
        "sc_pv": null,
        "sc_autos": null,
        "sc_dias_adicional": 0,
        "sc_modelo": "",
        "cap_pres": null,
        "cap_pres_falt": 0,
        "cap_online": null,
        "cap_online_falt": 0,
        "cap_id_viz": null,
        "cap_id_comp": null,
        "cap_cert1": null,
        "cap_cert2": null,
        "cap_uf": 38500,
        "cm_ot": null,
        "cm_envios": null,
        "cm_cotizacion": null,
        "cm_aprobado": null
      },
      "2025-10": {
        "p1_llave1": true,
        "p1_llave2": true,
        "p1_venta_rep": null,
        "p1_paso_veh": null,
        "p1_paso_veh_real": null,
        "p1_campanas": null,
        "p1_mpp": null,
        "p2_cumpl": null,
        "p2_vor_cargo": 0,
        "p2_facturacion": null,
        "p3_poliza": null,
        "p3_dyp": null,
        "p3_fact_seguros": null,
        "p3_fact_dyp": null,
        "p4_nps": null,
        "p4_tasa_resp": null,
        "p4_facturacion": null,
        "p4_n_resp": null,
        "p4_n_total": null,
        "sc_pv": null,
        "sc_autos": null,
        "sc_dias_adicional": 0,
        "sc_modelo": "",
        "cap_pres": null,
        "cap_pres_falt": 0,
        "cap_online": null,
        "cap_online_falt": 0,
        "cap_id_viz": null,
        "cap_id_comp": null,
        "cap_cert1": null,
        "cap_cert2": null,
        "cap_uf": 38500,
        "cm_ot": null,
        "cm_envios": null,
        "cm_cotizacion": null,
        "cm_aprobado": null
      },
      "2025-11": {
        "p1_llave1": true,
        "p1_llave2": true,
        "p1_venta_rep": null,
        "p1_paso_veh": null,
        "p1_paso_veh_real": null,
        "p1_campanas": null,
        "p1_mpp": null,
        "p2_cumpl": null,
        "p2_vor_cargo": 0,
        "p2_facturacion": null,
        "p3_poliza": null,
        "p3_dyp": null,
        "p3_fact_seguros": null,
        "p3_fact_dyp": null,
        "p4_nps": null,
        "p4_tasa_resp": null,
        "p4_facturacion": null,
        "p4_n_resp": null,
        "p4_n_total": null,
        "sc_pv": null,
        "sc_autos": null,
        "sc_dias_adicional": 0,
        "sc_modelo": "",
        "cap_pres": null,
        "cap_pres_falt": 0,
        "cap_online": null,
        "cap_online_falt": 0,
        "cap_id_viz": null,
        "cap_id_comp": null,
        "cap_cert1": null,
        "cap_cert2": null,
        "cap_uf": 38500,
        "cm_ot": null,
        "cm_envios": null,
        "cm_cotizacion": null,
        "cm_aprobado": null
      },
      "2025-12": {
        "p1_llave1": true,
        "p1_llave2": true,
        "p1_venta_rep": null,
        "p1_paso_veh": null,
        "p1_paso_veh_real": null,
        "p1_campanas": null,
        "p1_mpp": null,
        "p2_cumpl": null,
        "p2_vor_cargo": 0,
        "p2_facturacion": null,
        "p3_poliza": null,
        "p3_dyp": null,
        "p3_fact_seguros": null,
        "p3_fact_dyp": null,
        "p4_nps": null,
        "p4_tasa_resp": null,
        "p4_facturacion": null,
        "p4_n_resp": null,
        "p4_n_total": null,
        "sc_pv": null,
        "sc_autos": null,
        "sc_dias_adicional": 0,
        "sc_modelo": "",
        "cap_pres": null,
        "cap_pres_falt": 0,
        "cap_online": null,
        "cap_online_falt": 0,
        "cap_id_viz": null,
        "cap_id_comp": null,
        "cap_cert1": null,
        "cap_cert2": null,
        "cap_uf": 38500,
        "cm_ot": null,
        "cm_envios": null,
        "cm_cotizacion": null,
        "cm_aprobado": null
      },
      "2026-01": {
        "p1_llave1": true,
        "p1_llave2": true,
        "p1_venta_rep": null,
        "p1_paso_veh": null,
        "p1_paso_veh_real": null,
        "p1_campanas": null,
        "p1_mpp": null,
        "p2_cumpl": null,
        "p2_vor_cargo": 0,
        "p2_facturacion": null,
        "p3_poliza": null,
        "p3_dyp": null,
        "p3_fact_seguros": null,
        "p3_fact_dyp": null,
        "p4_nps": null,
        "p4_tasa_resp": null,
        "p4_facturacion": null,
        "p4_n_resp": null,
        "p4_n_total": null,
        "sc_pv": null,
        "sc_autos": null,
        "sc_dias_adicional": 0,
        "sc_modelo": "",
        "cap_pres": null,
        "cap_pres_falt": 0,
        "cap_online": null,
        "cap_online_falt": 0,
        "cap_id_viz": null,
        "cap_id_comp": null,
        "cap_cert1": null,
        "cap_cert2": null,
        "cap_uf": 38500,
        "cm_ot": null,
        "cm_envios": null,
        "cm_cotizacion": null,
        "cm_aprobado": null
      },
      "2026-02": {
        "p1_llave1": true,
        "p1_llave2": true,
        "p1_venta_rep": null,
        "p1_paso_veh": null,
        "p1_paso_veh_real": null,
        "p1_campanas": null,
        "p1_mpp": null,
        "p2_cumpl": null,
        "p2_vor_cargo": 0,
        "p2_facturacion": null,
        "p3_poliza": null,
        "p3_dyp": null,
        "p3_fact_seguros": null,
        "p3_fact_dyp": null,
        "p4_nps": null,
        "p4_tasa_resp": null,
        "p4_facturacion": null,
        "p4_n_resp": null,
        "p4_n_total": null,
        "sc_pv": null,
        "sc_autos": null,
        "sc_dias_adicional": 0,
        "sc_modelo": "",
        "cap_pres": null,
        "cap_pres_falt": 0,
        "cap_online": null,
        "cap_online_falt": 0,
        "cap_id_viz": null,
        "cap_id_comp": null,
        "cap_cert1": null,
        "cap_cert2": null,
        "cap_uf": 38500,
        "cm_ot": null,
        "cm_envios": null,
        "cm_cotizacion": null,
        "cm_aprobado": null
      },
      "2026-03": {
        "p1_llave1": true,
        "p1_llave2": true,
        "p1_venta_rep": null,
        "p1_paso_veh": null,
        "p1_paso_veh_real": null,
        "p1_campanas": null,
        "p1_mpp": null,
        "p2_cumpl": null,
        "p2_vor_cargo": 0,
        "p2_facturacion": null,
        "p3_poliza": null,
        "p3_dyp": null,
        "p3_fact_seguros": null,
        "p3_fact_dyp": null,
        "p4_nps": null,
        "p4_tasa_resp": null,
        "p4_facturacion": null,
        "p4_n_resp": null,
        "p4_n_total": null,
        "sc_pv": null,
        "sc_autos": null,
        "sc_dias_adicional": 0,
        "sc_modelo": "",
        "cap_pres": null,
        "cap_pres_falt": 0,
        "cap_online": null,
        "cap_online_falt": 0,
        "cap_id_viz": null,
        "cap_id_comp": null,
        "cap_cert1": null,
        "cap_cert2": null,
        "cap_uf": 38500,
        "cm_ot": null,
        "cm_envios": null,
        "cm_cotizacion": null,
        "cm_aprobado": null
      },
      "2026-04": {
        "p1_llave1": true,
        "p1_llave2": true,
        "p1_venta_rep": null,
        "p1_paso_veh": null,
        "p1_paso_veh_real": null,
        "p1_campanas": null,
        "p1_mpp": null,
        "p2_cumpl": null,
        "p2_vor_cargo": 0,
        "p2_facturacion": null,
        "p3_poliza": null,
        "p3_dyp": null,
        "p3_fact_seguros": null,
        "p3_fact_dyp": null,
        "p4_nps": null,
        "p4_tasa_resp": null,
        "p4_facturacion": null,
        "p4_n_resp": null,
        "p4_n_total": null,
        "sc_pv": null,
        "sc_autos": null,
        "sc_dias_adicional": 0,
        "sc_modelo": "",
        "cap_pres": null,
        "cap_pres_falt": 0,
        "cap_online": null,
        "cap_online_falt": 0,
        "cap_id_viz": null,
        "cap_id_comp": null,
        "cap_cert1": null,
        "cap_cert2": null,
        "cap_uf": 38500,
        "cm_ot": null,
        "cm_envios": null,
        "cm_cotizacion": null,
        "cm_aprobado": null
      },
      "2026-06": {
        "p1_llave1": true,
        "p1_llave2": true,
        "p1_venta_rep": null,
        "p1_paso_veh": null,
        "p1_paso_veh_real": null,
        "p1_campanas": null,
        "p1_mpp": null,
        "p2_cumpl": null,
        "p2_vor_cargo": 0,
        "p2_facturacion": null,
        "p3_poliza": null,
        "p3_dyp": null,
        "p3_fact_seguros": null,
        "p3_fact_dyp": null,
        "p4_nps": null,
        "p4_tasa_resp": null,
        "p4_facturacion": null,
        "p4_n_resp": null,
        "p4_n_total": null,
        "sc_pv": null,
        "sc_autos": null,
        "sc_dias_adicional": 0,
        "sc_modelo": "",
        "cap_pres": null,
        "cap_pres_falt": 0,
        "cap_online": null,
        "cap_online_falt": 0,
        "cap_id_viz": null,
        "cap_id_comp": null,
        "cap_cert1": null,
        "cap_cert2": null,
        "cap_uf": 38500,
        "cm_ot": null,
        "cm_envios": null,
        "cm_cotizacion": null,
        "cm_aprobado": null
      }
    }
  }
}